portier/__init__.py
portier/client.py
portier/utils.py
portier_python-0.1.1.dist-info/DESCRIPTION.rst
portier_python-0.1.1.dist-info/METADATA
portier_python-0.1.1.dist-info/RECORD
portier_python-0.1.1.dist-info/WHEEL
portier_python-0.1.1.dist-info/metadata.json
portier_python-0.1.1.dist-info/top_level.txt
