Metadata-Version: 2.0
Name: portier-python
Version: 0.1.1
Summary: Portier authentication Python helpers.
Home-page: https://github.com/portier/portier-python
Author: Mozilla Services
Author-email: services-dev@mozilla.com
License: Apache License (2.0)
Keywords: web services
Platform: UNKNOWN
Classifier: Programming Language :: Python
Classifier: Programming Language :: Python :: 2.7
Classifier: Programming Language :: Python :: 3.4
Classifier: Programming Language :: Python :: 3.5
Classifier: Topic :: Internet :: WWW/HTTP
Classifier: Topic :: Internet :: WWW/HTTP :: WSGI :: Application
Classifier: License :: OSI Approved :: Apache Software License
Requires-Dist: PyJWT
Requires-Dist: cryptography
Requires-Dist: requests
